gnu_mo_files/__init__.py
gnu_mo_files-0.0.1.dist-info/LICENSE
gnu_mo_files-0.0.1.dist-info/METADATA
gnu_mo_files-0.0.1.dist-info/WHEEL
gnu_mo_files-0.0.1.dist-info/top_level.txt
gnu_mo_files-0.0.1.dist-info/RECORD
