Metadata-Version: 2.1
Name: gnu-mo-files
Version: 0.0.1
Summary: Read and write GNU MO files
Home-page: https://github.com/stsav012/gnu_mo_files
Author: StSav012
Author-email: stsav012@gmail.com
License: UNKNOWN
Project-URL: Bug Tracker, https://github.com/stsav012/gnu_mo_files/issues
Platform: UNKNOWN
Classifier: Development Status :: 4 - Beta
Classifier: Programming Language :: Python :: 3.6
Classifier: Typing :: Typed
Classifier: License :: OSI Approved :: The Unlicense (Unlicense)
Classifier: Operating System :: OS Independent
Classifier: Intended Audience :: Developers
Classifier: Topic :: Software Development :: Localization
Requires-Python: >=3.6
License-File: LICENSE
